velotrain.py
velotrain-1.0.3.dist-info/licenses/LICENSE
velotrain-1.0.3.dist-info/METADATA
velotrain-1.0.3.dist-info/WHEEL
velotrain-1.0.3.dist-info/entry_points.txt
velotrain-1.0.3.dist-info/top_level.txt
velotrain-1.0.3.dist-info/RECORD
