Metadata-Version: 2.4
Name: velotrain
Version: 1.0.3
Summary: Velodrome transponder training timing
Author-email: Nathan Fraser <ndf-zz@6-v.org>
License-Expression: MIT
Project-URL: homepage, https://github.com/ndf-zz/velotrain
Project-URL: repository, https://github.com/ndf-zz/velotrain
Keywords: velodrome,transponder,timing
Classifier: Development Status :: 3 - Alpha
Classifier: Topic :: Other/Nonlisted Topic
Classifier: Operating System :: OS Independent
Classifier: Programming Language :: Python :: 3
Requires-Python: >=3.11
License-File: LICENSE
Requires-Dist: metarace<2.2,>=2.1.15
Requires-Dist: ypmeteo
Dynamic: license-file
